<?xml version="1.0" encoding="UTF-8"?>
<hazelcast
        xsi:schemaLocation="http://www.hazelcast.com/schema/config http://www.hazelcast.com/schema/config/hazelcast-config-3.10.xsd"
        xmlns="http://www.hazelcast.com/schema/config"
        xmlns:xsi="http://www.w3.org/2001/XMLSchema-instance">

    <properties>
        <property name="hazelcast.icmp.enabled">true</property>
        <property name="hazelcast.icmp.timeout">100</property>
        <property name="hazelcast.icmp.interval">1000</property>
        <property name="hazelcast.icmp.ttl">255</property>
    </properties>

    <group>
        <name>hz-icmp</name>
        <password>s3crEt</password>
    </group>

</hazelcast>